tazids/__init__.py
tazids/clustering.py
tazids/regressor.py
tazids/tree.py
tazids-1.2.0.dist-info/METADATA
tazids-1.2.0.dist-info/WHEEL
tazids-1.2.0.dist-info/top_level.txt
tazids-1.2.0.dist-info/RECORD
