Metadata-Version: 2.1
Name: tazids
Version: 1.2.0
Summary: A simple machine learning library for educational purposes.
Home-page: https://github.com/mohannadtazi/tazi_ds
Author: TAZI Mohannad
Author-email: mohannadtazi.dev@gmail.com
License: MIT
Classifier: Programming Language :: Python :: 3
Classifier: License :: OSI Approved :: MIT License
Classifier: Operating System :: OS Independent
Requires-Python: >=3.6
Requires-Dist: numpy
